giskard_lmutils/__init__.py
giskard_lmutils/clustering/__init__.py
giskard_lmutils/clustering/find_topic.py
giskard_lmutils/model/__init__.py
giskard_lmutils/model/litellm.py
giskard_lmutils-1.0.0.dist-info/METADATA
giskard_lmutils-1.0.0.dist-info/WHEEL
giskard_lmutils-1.0.0.dist-info/licenses/LICENSE
giskard_lmutils-1.0.0.dist-info/RECORD
