Metadata-Version: 2.4
Name: giskard-lmutils
Version: 1.0.0
Summary: Giskard LLM Utils
Author-email: Kevin Messiaen <kevin@giskard.ai>
License: Apache Software License 2.0
License-File: LICENSE
Requires-Python: <3.14,>=3.10
Requires-Dist: litellm>=1.59.3
Requires-Dist: numpy>=2.2.2
Provides-Extra: local-embedding
Requires-Dist: torch>=2.6.0; extra == 'local-embedding'
Requires-Dist: transformers>=4.51.3; extra == 'local-embedding'
